rockart_examples/__init__.py
rockart_examples/exceptions.py
rockart_examples/life/__init__.py
rockart_examples/life/entry.py
rockart_examples/life/game.py
rockart_examples/life/gui.py
rockart_examples-0.2.1.dist-info/LICENSE
rockart_examples-0.2.1.dist-info/METADATA
rockart_examples-0.2.1.dist-info/WHEEL
rockart_examples-0.2.1.dist-info/entry_points.txt
rockart_examples-0.2.1.dist-info/top_level.txt
rockart_examples-0.2.1.dist-info/zip-safe
rockart_examples-0.2.1.dist-info/RECORD
